faraday/__init__.py
faraday/aprs.py
faraday/configure.py
faraday/data.py
faraday/deviceconfiguration.py
faraday/hermesflaskserver.py
faraday/proxy.py
faraday/simpleconfig.py
faraday/simpleui.py
faraday/telemetry.py
faraday/classes/__init__.py
faraday/classes/helper.py
faraday/hermes/__init__.py
faraday/hermes/hermesmessage.py
faraday/hermes/hermesobject.py
faraday/proxyio/Checksum.py
faraday/proxyio/__init__.py
faraday/proxyio/cc430radioconfig.py
faraday/proxyio/commandmodule.py
faraday/proxyio/deviceconfig.py
faraday/proxyio/faradaybasicproxyio.py
faraday/proxyio/faradaycommands.py
faraday/proxyio/gpioallocations.py
faraday/proxyio/telemetryparser.py
faraday/static/jquery-3.2.0.js
faraday/static/simpleui.js
faraday/static/bootstrap-3.3.7-dist/css/bootstrap-theme.css
faraday/static/bootstrap-3.3.7-dist/css/bootstrap-theme.css.map
faraday/static/bootstrap-3.3.7-dist/css/bootstrap-theme.min.css
faraday/static/bootstrap-3.3.7-dist/css/bootstrap-theme.min.css.map
faraday/static/bootstrap-3.3.7-dist/css/bootstrap.css
faraday/static/bootstrap-3.3.7-dist/css/bootstrap.css.map
faraday/static/bootstrap-3.3.7-dist/css/bootstrap.min.css
faraday/static/bootstrap-3.3.7-dist/css/bootstrap.min.css.map
faraday/static/bootstrap-3.3.7-dist/fonts/glyphicons-halflings-regular.eot
faraday/static/bootstrap-3.3.7-dist/fonts/glyphicons-halflings-regular.svg
faraday/static/bootstrap-3.3.7-dist/fonts/glyphicons-halflings-regular.ttf
faraday/static/bootstrap-3.3.7-dist/fonts/glyphicons-halflings-regular.woff
faraday/static/bootstrap-3.3.7-dist/fonts/glyphicons-halflings-regular.woff2
faraday/static/bootstrap-3.3.7-dist/js/bootstrap.js
faraday/static/bootstrap-3.3.7-dist/js/bootstrap.min.js
faraday/static/bootstrap-3.3.7-dist/js/npm.js
faraday/templates/index.html
faraday/templates/layout.html
faraday/uart/__init__.py
faraday/uart/layer_2_protocol.py
faraday/uart/layer_2_service.py
faraday/uart/layer_4_protocol.py
faraday-0.0.1018.dev1438.dist-info/DESCRIPTION.rst
faraday-0.0.1018.dev1438.dist-info/METADATA
faraday-0.0.1018.dev1438.dist-info/RECORD
faraday-0.0.1018.dev1438.dist-info/WHEEL
faraday-0.0.1018.dev1438.dist-info/entry_points.txt
faraday-0.0.1018.dev1438.dist-info/metadata.json
faraday-0.0.1018.dev1438.dist-info/pbr.json
faraday-0.0.1018.dev1438.dist-info/top_level.txt
