Metadata-Version: 2.0
Name: faraday
Version: 0.0.1018.dev1438
Summary: FaradayRF amateur radio open source software
Home-page: https://github.com/FaradayRF/Faraday-Software
Author: FaradayRF
Author-email: Support@FaradayRF.com
License: GPLv3
Keywords: faraday
Requires-Dist: appdirs (>=1.4.3)
Requires-Dist: click (>=6.7)
Requires-Dist: configparser (>=3.5.0)
Requires-Dist: enum34 (>=1.1.6)
Requires-Dist: flake8 (>=3.3.0)
Requires-Dist: Flask (>=0.12)
Requires-Dist: Flask-Cors (>=3.0.2)
Requires-Dist: itsdangerous (>=0.24)
Requires-Dist: Jinja2 (>=2.9.4)
Requires-Dist: MarkupSafe (>=0.23)
Requires-Dist: mccabe (>=0.6.1)
Requires-Dist: packaging (>=16.8)
Requires-Dist: py (>=1.4.33)
Requires-Dist: pycodestyle (>=2.3.1)
Requires-Dist: pyflakes (>=1.5.0)
Requires-Dist: pyparsing (>=2.2.0)
Requires-Dist: pyserial (>=3.2.1)
Requires-Dist: pytest (>=3.0.7)
Requires-Dist: pytest-flake8 (>=0.8.1)
Requires-Dist: requests (>=2.12.5)
Requires-Dist: six (>=1.10.0)
Requires-Dist: Werkzeug (>=0.11.15)
Requires-Dist: aprslib (>=0.6.46)
